[
  {
    "username": "ADMIN",
    "password": "MTsN01Payakumbuh",
    "email": "skyzeecorp@gmail.com",
    "phone": "79828950162",
    "status": "active",
    "otp": "488293",
    "isPremium": true,
    "tokenVip": "",
    "usage": 0,
    "lastReset": "2026-04-12"
  },
  {
    "username": "Ryuujin ",
    "password": "ryuujin123",
    "phone": "089925545200",
    "status": "active",
    "otp": "863472",
    "isPremium": false,
    "tokenVip": "",
    "usage": 0,
    "lastReset": "2026-04-12"
  },
  {
    "username": "Leo Arthur",
    "password": "informatika11",
    "phone": "62831618801444",
    "status": "active",
    "otp": "685925",
    "isPremium": false,
    "tokenVip": "",
    "usage": 5,
    "lastReset": "2026-04-14"
  },
  {
    "username": "rezkaa",
    "password": "achaaimup",
    "email": "skyzeecorp@gmail.com",
    "phone": "48666666672",
    "status": "active",
    "otp": "888594",
    "isPremium": false,
    "usage": 3,
    "lastReset": "2026-04-14"
  }
]